[
    {
        "name": "Grupo Parra Rangel",
        "years": "2018 - 2019",
        "image": "/companies/gpr.jpeg",
        "logo": "/companies/gpr.jpeg",
        "projects": [
            {
                "name": "Internal tools"
            },
            {
                "name": "Mithra Mexico"
            }
        ]
    },
    {
        "name": "ADES Technologies",
        "years": "2019 - 2019",
        "image": "/companies/adestech.png",
        "logo": "/companies/adestech_logo.jpeg",
        "projects": [
            {
                "name": "Gigaaa virtual assistant mobile app"
            },
            {
                "name": "Gigaaa virtual assistant web app"
            },
            {
                "name": "Gigaaa smart mirror"
            }
        ]
    },
    {
        "name": "AlphaCredit",
        "years": "2019 - 2021",
        "image": "/companies/alphacredit.png",
        "logo": "/companies/alphacredit_logo.png",
        "projects": [
            {
                "name": "Prospection table"
            },
            {
                "name": "Bontu"
            }
        ]
    },
    {
        "name": "Globant",
        "years": "2021 - Present",
        "image": "/companies/globant.png",
        "logo": "/companies/globant_logo.png",
        "projects": [
            {
                "name": "LA Clippers ( Nov. 2023 - Present )",
                "url": "https://intuitdome.com/"
            },
            {
                "name": "Deloitte ( Jul. 2022 - Nov. 2023 )",
                "url": "https://www2.deloitte.com/global/en.html"
            },
            {
                "name": "Telecom (Mar. 2021 - Jul. 2022)",
                "url": "https://www.personal.com.ar/"
            }
        ]
    }
]
